pygomoku/__init__.py
pygomoku/gui.py
pygomoku/main.py
pygomoku/score.py
pygomoku/board/__init__.py
pygomoku/board/abstract.py
pygomoku/board/alpha.py
pygomoku/board/heuristic.py
pygomoku/board/mcts.py
pygomoku/board/minmax.py
pygomoku/board/simple.py
pygomoku-1.0.0.dist-info/LICENSE
pygomoku-1.0.0.dist-info/WHEEL
pygomoku-1.0.0.dist-info/METADATA
pygomoku-1.0.0.dist-info/RECORD
