Metadata-Version: 2.3
Name: pygomoku
Version: 1.0.0
Summary: Gomoku game with AI
Author-email: Rui HE <daniel.saturday@icloud.com>
Requires-Python: >=3.10
Classifier: License :: OSI Approved :: MIT License
Requires-Dist: pygame  >=2.6.0, <3.0
Requires-Dist: black ; extra == "development"
Requires-Dist: isort ; extra == "development"
Requires-Dist: mypy ; extra == "development"
Requires-Dist: pre-commit ; extra == "development"
Requires-Dist: pyright ; extra == "development"
Provides-Extra: development
